wavewhisper/__init__.py
wavewhisper/audio.py
wavewhisper/character.py
wavewhisper/message.py
WaveWhisper-1.0.2.dist-info/LICENSE
WaveWhisper-1.0.2.dist-info/METADATA
WaveWhisper-1.0.2.dist-info/WHEEL
WaveWhisper-1.0.2.dist-info/top_level.txt
WaveWhisper-1.0.2.dist-info/RECORD
