Metadata-Version: 2.1
Name: WaveWhisper
Version: 1.0.2
Summary: Steganographic encryption within audio spectrograms
Home-page: https://github.com/maxmmueller/wavewhisper
Author: Maximilian Müller
License: Apache License 2.0
Keywords: audio,python,encryption,waveform,wav,steganography
Classifier: Intended Audience :: Developers
Classifier: Programming Language :: Python :: 3
Classifier: Operating System :: OS Independent
License-File: LICENSE
